LICENSE
MANIFEST.in
README.rst
pyproject.toml
setup.cfg
setup.py
django_y_swagger_ui.egg-info/PKG-INFO
django_y_swagger_ui.egg-info/SOURCES.txt
django_y_swagger_ui.egg-info/dependency_links.txt
django_y_swagger_ui.egg-info/requires.txt
django_y_swagger_ui.egg-info/top_level.txt
y_swagger_ui/__init__.py
y_swagger_ui/admin.py
y_swagger_ui/apps.py
y_swagger_ui/models.py
y_swagger_ui/tests.py
y_swagger_ui/urls.py
y_swagger_ui/views.py
y_swagger_ui/migrations/__init__.py
y_swagger_ui/static/y_swagger_ui/swagger-ui-bundle.js
y_swagger_ui/static/y_swagger_ui/swagger-ui-standalone-preset.js
y_swagger_ui/static/y_swagger_ui/swagger-ui.css
y_swagger_ui/templates/y_swagger_ui/swagger_ui.html