Metadata-Version: 2.1
Name: django-y-swagger-ui
Version: 1.0.1
Summary: A Django app to show swagger ui for OpenAPI specification.
Home-page: https://github.com/zyunx/django-y-swagger-ui
Author: Zhang Yun
Author-email: zyunx.net@gmail.com
License: MIT
Classifier: Environment :: Web Environment
Classifier: Framework :: Django
Classifier: Intended Audience :: Developers
Classifier: Operating System :: OS Independent
Classifier: Programming Language :: Python
Classifier: Programming Language :: Python :: 3
Classifier: Programming Language :: Python :: 3 :: Only
Classifier: Topic :: Internet :: WWW/HTTP
Classifier: Topic :: Internet :: WWW/HTTP :: Dynamic Content
Requires-Python: >=3.11
License-File: LICENSE
